{
  "version": "0.0.1",
  "catchAll": {
    "next": []
  },
  "startNode": "entry",
  "skillData": {
    "contentId": "builtin_single-choice-t7W08Z",
    "keywords": {
      "product": [
        "product",
        "What product do you sold ?"
      ],
      "contact": [
        "contact",
        "What is your email ?"
      ]
    },
    "config": {}
  },
  "nodes": [
    {
      "name": "entry",
      "onEnter": [
        "say #!builtin_single-choice-t7W08Z {\"skill\":\"choice\"}"
      ],
      "next": [
        {
          "condition": "true",
          "node": "parse"
        }
      ],
      "id": "793520"
    },
    {
      "name": "parse",
      "onReceive": [
        "basic-skills/choice_parse_answer {\"contentId\":\"builtin_single-choice-t7W08Z\",\"keywords\":{\"product\":[\"product\",\"What product do you sold ?\"],\"contact\":[\"contact\",\"What is your email ?\"]},\"config\":{}}"
      ],
      "next": [
        {
          "condition": "temp['skill-choice-valid'] === true",
          "node": "#"
        },
        {
          "condition": "true",
          "node": "invalid"
        }
      ],
      "onEnter": [],
      "id": "646324"
    },
    {
      "name": "invalid",
      "onEnter": [
        "basic-skills/choice_invalid_answer"
      ],
      "next": [
        {
          "condition": "temp['skill-choice-invalid-count'] <= undefined",
          "node": "sorry"
        },
        {
          "condition": "true",
          "node": "#"
        }
      ],
      "id": "778371"
    },
    {
      "name": "sorry",
      "onEnter": [
        "say #!builtin_single-choice-t7W08Z {\"skill\":\"choice\"}"
      ],
      "next": [
        {
          "condition": "true",
          "node": "parse"
        }
      ],
      "id": "115141"
    }
  ]
}